{
"bounds": [326000.000000, 5730000.000000, 13.650000, 326999.990000, 5730999.990000, 1013.640000],
"boundsConforming": [326000.000000, 5730000.000000, 13.650000, 326999.990000, 5730999.990000, 193.300000],
"dataType": "laszip",
"hierarchyType": "json",
"points": 7205708,
"span": 128,
"version": "1.0.0",
"schema": [
	{"name": "X", "type": "float", "scale": 0.01, "offset": 326500, "size": 8, "count": 7205708, "maximum": 327000, "minimum": 326000, "mean": 326502, "stddev": 284.469, "variance": 80922.4},
	{"name": "Y", "type": "float", "scale": 0.01, "offset": 5.7305e+06, "size": 8, "count": 7205708, "maximum": 5.731e+06, "minimum": 5.73e+06, "mean": 5.7305e+06, "stddev": 285.513, "variance": 81517.4},
	{"name": "Z", "type": "float", "scale": 0.01, "offset": 513.645, "size": 8, "count": 7205708, "maximum": 193.3, "minimum": 13.65, "mean": 19.6132, "stddev": 3.91191, "variance": 15.3031},
	{"name": "Intensity", "type": "unsigned", "size": 2, "count": 7205708, "maximum": 65535, "minimum": 0, "mean": 38892.2, "stddev": 11995.3, "variance": 1.43886e+08},
	{"name": "ReturnNumber", "type": "unsigned", "size": 1, "count": 7205708, "maximum": 7, "minimum": 0, "mean": 1.22298, "stddev": 0.706506, "variance": 0.499151},
	{"name": "NumberOfReturns", "type": "unsigned", "size": 1, "count": 7205708, "maximum": 7, "minimum": 0, "mean": 1.45544, "stddev": 1.09538, "variance": 1.19987},
	{"name": "ScanChannel", "type": "unsigned", "size": 1, "count": 7205708, "maximum": 0, "minimum": 0, "mean": 0, "stddev": 0, "variance": 0},
	{"name": "ScanDirectionFlag", "type": "unsigned", "size": 1, "count": 7205708, "maximum": 0, "minimum": 0, "mean": 0, "stddev": 0, "variance": 0},
	{"name": "PointSourceId", "type": "unsigned", "size": 2, "count": 7205708, "maximum": 541, "minimum": 0, "mean": 523.556, "stddev": 45.4984, "variance": 2070.1},
	{"name": "Classification", "type": "unsigned", "size": 1, "counts": [ {"value": 1, "count": 1256413}, {"value": 6, "count": 107501}, {"value": 2, "count": 5806709}, {"value": 18, "count": 21}, {"value": 9, "count": 35064}], "count": 7205708, "maximum": 18, "minimum": 1, "mean": 1.91942, "stddev": 0.803592, "variance": 0.64576},
	{"name": "EdgeOfFlightLine", "type": "unsigned", "size": 1, "count": 7205708, "maximum": 1, "minimum": 0, "mean": 0.000102696, "stddev": 0.0101334, "variance": 0.000102686},
	{"name": "ScanAngleRank", "type": "float", "size": 4, "count": 7205708, "maximum": 0, "minimum": 0, "mean": 0, "stddev": 0, "variance": 0},
	{"name": "UserData", "type": "unsigned", "size": 1, "count": 7205708, "maximum": 24, "minimum": 0, "mean": 4.42963, "stddev": 0.853093, "variance": 0.727768},
	{"name": "GpsTime", "type": "float", "size": 8, "count": 7205708, "maximum": 2.65113e+08, "minimum": 0, "mean": 2.63141e+08, "stddev": 2.27704e+07, "variance": 5.18491e+14},
	{"name": "Red", "type": "unsigned", "size": 2, "count": 7205708, "maximum": 0, "minimum": 0, "mean": 0, "stddev": 0, "variance": 0},
	{"name": "Green", "type": "unsigned", "size": 2, "count": 7205708, "maximum": 0, "minimum": 0, "mean": 0, "stddev": 0, "variance": 0},
	{"name": "Blue", "type": "unsigned", "size": 2, "count": 7205708, "maximum": 0, "minimum": 0, "mean": 0, "stddev": 0, "variance": 0},
	{"name": "Infrared", "type": "unsigned", "size": 2, "count": 7205708, "maximum": 0, "minimum": 0, "mean": 0, "stddev": 0, "variance": 0},
	{"name": "ClassFlags", "type": "unsigned", "size": 1, "count": 7205708, "maximum": 1, "minimum": 0, "mean": 0.00743244, "stddev": 0.0858906, "variance": 0.0073772}
],
"srs": {
}
}
