{
"bounds": [325999.910000, 5728999.900000, 13.550000, 327000.080000, 5730000.070000, 1013.720000],
"boundsConforming": [325999.910000, 5728999.900000, 13.550000, 327000.080000, 5730000.060000, 176.130000],
"dataType": "laszip",
"hierarchyType": "json",
"points": 5671265,
"span": 128,
"version": "1.0.0",
"schema": [
	{"name": "X", "type": "float", "scale": 0.01, "offset": 326500, "size": 8, "count": 5671265, "maximum": 327000, "minimum": 326000, "mean": 326413, "stddev": 278.395, "variance": 77503.8},
	{"name": "Y", "type": "float", "scale": 0.01, "offset": 5.7295e+06, "size": 8, "count": 5671265, "maximum": 5.73e+06, "minimum": 5.729e+06, "mean": 5.72951e+06, "stddev": 277.614, "variance": 77069.5},
	{"name": "Z", "type": "float", "scale": 0.01, "offset": 513.635, "size": 8, "count": 5671265, "maximum": 176.13, "minimum": 13.55, "mean": 18.6705, "stddev": 4.49747, "variance": 20.2273},
	{"name": "Intensity", "type": "unsigned", "size": 2, "count": 5671265, "maximum": 0, "minimum": 0, "mean": 0, "stddev": 0, "variance": 0},
	{"name": "ReturnNumber", "type": "unsigned", "size": 1, "count": 5671265, "maximum": 7, "minimum": 0, "mean": 1.2794, "stddev": 0.845829, "variance": 0.715426},
	{"name": "NumberOfReturns", "type": "unsigned", "size": 1, "count": 5671265, "maximum": 7, "minimum": 0, "mean": 1.59307, "stddev": 1.28682, "variance": 1.65591},
	{"name": "ScanChannel", "type": "unsigned", "size": 1, "count": 5671265, "maximum": 0, "minimum": 0, "mean": 0, "stddev": 0, "variance": 0},
	{"name": "ScanDirectionFlag", "type": "unsigned", "size": 1, "count": 5671265, "maximum": 0, "minimum": 0, "mean": 0, "stddev": 0, "variance": 0},
	{"name": "PointSourceId", "type": "unsigned", "size": 2, "count": 5671265, "maximum": 0, "minimum": 0, "mean": 0, "stddev": 0, "variance": 0},
	{"name": "Classification", "type": "unsigned", "size": 1, "counts": [ {"value": 5, "count": 795358}, {"value": 7, "count": 301812}, {"value": 6, "count": 163498}, {"value": 3, "count": 178693}, {"value": 2, "count": 4203458}, {"value": 1, "count": 28446}], "count": 5671265, "maximum": 7, "minimum": 1, "mean": 2.82863, "stddev": 1.55042, "variance": 2.4038},
	{"name": "EdgeOfFlightLine", "type": "unsigned", "size": 1, "count": 5671265, "maximum": 1, "minimum": 0, "mean": 0.000500594, "stddev": 0.0223684, "variance": 0.000500343},
	{"name": "ScanAngleRank", "type": "float", "size": 4, "count": 5671265, "maximum": 0, "minimum": 0, "mean": 0, "stddev": 0, "variance": 0},
	{"name": "UserData", "type": "unsigned", "size": 1, "count": 5671265, "maximum": 255, "minimum": 0, "mean": 14.7929, "stddev": 37.1579, "variance": 1380.71},
	{"name": "GpsTime", "type": "float", "size": 8, "count": 5671265, "maximum": 0, "minimum": 0, "mean": 0, "stddev": 0, "variance": 0},
	{"name": "Red", "type": "unsigned", "size": 2, "count": 5671265, "maximum": 0, "minimum": 0, "mean": 0, "stddev": 0, "variance": 0},
	{"name": "Green", "type": "unsigned", "size": 2, "count": 5671265, "maximum": 0, "minimum": 0, "mean": 0, "stddev": 0, "variance": 0},
	{"name": "Blue", "type": "unsigned", "size": 2, "count": 5671265, "maximum": 0, "minimum": 0, "mean": 0, "stddev": 0, "variance": 0},
	{"name": "Infrared", "type": "unsigned", "size": 2, "count": 5671265, "maximum": 0, "minimum": 0, "mean": 0, "stddev": 0, "variance": 0},
	{"name": "ClassFlags", "type": "unsigned", "size": 1, "count": 5671265, "maximum": 1, "minimum": 0, "mean": 0.0322244, "stddev": 0.176596, "variance": 0.031186}
],
"srs": {
}
}
